pep562/__init__.py
pep562/__meta__.py
pep562-1.0b1.dist-info/LICENSE.md
pep562-1.0b1.dist-info/METADATA
pep562-1.0b1.dist-info/WHEEL
pep562-1.0b1.dist-info/top_level.txt
pep562-1.0b1.dist-info/RECORD
