Metadata-Version: 2.1
Name: pep562
Version: 1.0b1
Summary: Backport of PEP 562.
Home-page: https://github.com/facelessuser/pep562
Author: Isaac Muse
Author-email: Isaac.Muse@gmail.com
License: MIT License
Keywords: pep 562 backport
Platform: UNKNOWN
Classifier: Development Status :: 4 - Beta
Classifier: Intended Audience :: Developers
Classifier: License :: OSI Approved :: MIT License
Classifier: Operating System :: OS Independent
Classifier: Programming Language :: Python :: 2
Classifier: Programming Language :: Python :: 2.7
Classifier: Programming Language :: Python :: 3
Classifier: Programming Language :: Python :: 3.3
Classifier: Programming Language :: Python :: 3.4
Classifier: Programming Language :: Python :: 3.5
Classifier: Programming Language :: Python :: 3.6
Classifier: Programming Language :: Python :: 3.7
